LICENSE
MANIFEST.in
README.md
setup.py
xebec/__init__.py
xebec.egg-info/PKG-INFO
xebec.egg-info/SOURCES.txt
xebec.egg-info/dependency_links.txt
xebec.egg-info/entry_points.txt
xebec.egg-info/requires.txt
xebec.egg-info/top_level.txt
xebec/cli/__init__.py
xebec/cli/cli.py
xebec/cli/__pycache__/__init__.cpython-38.pyc
xebec/cli/__pycache__/cli.cpython-38.pyc
xebec/config/alpha_div_metrics.tsv
xebec/config/beta_div_metrics.tsv
xebec/js/chosen_col_callback.js
xebec/src/__init__.py
xebec/src/_concatenate.py
xebec/src/_depth.py
xebec/src/_validate.py
xebec/src/_visualization.py
xebec/template/Snakefile.jinja2
xebec/template/config.yaml.jinja2
xebec/workflow/Snakefile
xebec/workflow/.snakemake/log/2022-06-08T140955.743362.snakemake.log
xebec/workflow/rules/alpha_diversity.smk
xebec/workflow/rules/beta_diversity.smk
xebec/workflow/rules/common.smk
xebec/workflow/rules/evident.smk
xebec/workflow/rules/preprocess_data.smk
xebec/workflow/rules/visualization.smk
xebec/workflow/scripts/alpha_diversity.py
xebec/workflow/scripts/beta_diversity.py
xebec/workflow/scripts/concatenate.py
xebec/workflow/scripts/filter_metadata.py
xebec/workflow/scripts/interactive_effect_sizes.py
xebec/workflow/scripts/interactive_pw_effect_sizes.py
xebec/workflow/scripts/rarefy.py
xebec/workflow/scripts/run_evident.py