Metadata-Version: 2.1
Name: xebec
Version: 0.5.1
Summary: Snakemake pipeline for microbiome diversity effect size benchmarking.
Home-page: https://github.com/gibsramen/xebec
Author: Gibraan Rahman
Author-email: grahman@eng.ucsd.edu
License: BSD-3-Clause
Platform: UNKNOWN
Classifier: Development Status :: 3 - Alpha
Classifier: License :: OSI Approved :: BSD License
Classifier: Topic :: Software Development :: Libraries
Classifier: Topic :: Scientific/Engineering
Classifier: Topic :: Scientific/Engineering :: Bio-Informatics
Classifier: Programming Language :: Python :: 3
Classifier: Programming Language :: Python :: 3 :: Only
Classifier: Operating System :: Unix
Classifier: Operating System :: POSIX
Classifier: Operating System :: MacOS :: MacOS X
License-File: LICENSE
